roksta/__init__.cpython-314t-aarch64-linux-gnu.so
roksta/analytics.cpython-314t-aarch64-linux-gnu.so
roksta/append_usage_jsonl.cpython-314t-aarch64-linux-gnu.so
roksta/balance.cpython-314t-aarch64-linux-gnu.so
roksta/build_project.cpython-314t-aarch64-linux-gnu.so
roksta/chat_workflow.cpython-314t-aarch64-linux-gnu.so
roksta/check_for_updates.cpython-314t-aarch64-linux-gnu.so
roksta/check_subtask_sequence.cpython-314t-aarch64-linux-gnu.so
roksta/checkpoints.cpython-314t-aarch64-linux-gnu.so
roksta/clarify_goal.cpython-314t-aarch64-linux-gnu.so
roksta/codebase.cpython-314t-aarch64-linux-gnu.so
roksta/codebase_listing.cpython-314t-aarch64-linux-gnu.so
roksta/compatibility.cpython-314t-aarch64-linux-gnu.so
roksta/completions.cpython-314t-aarch64-linux-gnu.so
roksta/db.cpython-314t-aarch64-linux-gnu.so
roksta/discover_test_command.cpython-314t-aarch64-linux-gnu.so
roksta/enums.cpython-314t-aarch64-linux-gnu.so
roksta/env.cpython-314t-aarch64-linux-gnu.so
roksta/exceptions.cpython-314t-aarch64-linux-gnu.so
roksta/extended_text_area.cpython-314t-aarch64-linux-gnu.so
roksta/firebase.cpython-314t-aarch64-linux-gnu.so
roksta/firebase_auth_web.cpython-314t-aarch64-linux-gnu.so
roksta/firebase_config.cpython-314t-aarch64-linux-gnu.so
roksta/fix_tests.cpython-314t-aarch64-linux-gnu.so
roksta/gen_codebase_summaries.cpython-314t-aarch64-linux-gnu.so
roksta/gen_file_summaries.cpython-314t-aarch64-linux-gnu.so
roksta/gen_files_manifest.cpython-314t-aarch64-linux-gnu.so
roksta/gen_folder_summaries.cpython-314t-aarch64-linux-gnu.so
roksta/gen_one_line_goal.cpython-314t-aarch64-linux-gnu.so
roksta/gen_subtasks.cpython-314t-aarch64-linux-gnu.so
roksta/get_failing_tests.cpython-314t-aarch64-linux-gnu.so
roksta/get_prev_goal_context.cpython-314t-aarch64-linux-gnu.so
roksta/goal_workflow.cpython-314t-aarch64-linux-gnu.so
roksta/init_codebase.cpython-314t-aarch64-linux-gnu.so
roksta/lint_code.cpython-314t-aarch64-linux-gnu.so
roksta-0.4.22.dist-info/METADATA
roksta-0.4.22.dist-info/WHEEL
roksta-0.4.22.dist-info/entry_points.txt
roksta-0.4.22.dist-info/top_level.txt
roksta-0.4.22.dist-info/RECORD
