Metadata-Version: 2.4
Name: roksta
Version: 0.4.22
Summary: An AI coding assistant
Author-email: Prash Naidu <prash@roksta.ai>
Project-URL: Homepage, https://roksta.ai
Requires-Python: <3.15,>=3.11
Requires-Dist: google-genai==1.49.0
Requires-Dist: pydantic>=2.11.7
Requires-Dist: tiktoken>=0.9.0
Requires-Dist: rich>=14.0.0
Requires-Dist: pyyaml>=6.0.2
Requires-Dist: textual>=3.5.0
Requires-Dist: cryptography>=45.0.4
Requires-Dist: httpx>=0.28.1
Requires-Dist: ulid-py>=1.1.0
Requires-Dist: packaging>=25.0
Requires-Dist: pyperclip>=1.9.0
Requires-Dist: filetype>=1.2.0
Requires-Dist: gitpython>=3.1.44
Requires-Dist: jsonref>=1.1.0
Requires-Dist: pathspec>=0.12.1
Requires-Dist: psutil>=7.1.0
Requires-Dist: PyNaCl>=1.6.0
Requires-Dist: markdownify>=1.2.0
Requires-Dist: aiosqlite>=0.22.0
Provides-Extra: tests
Requires-Dist: pytest>=8.4.1; extra == "tests"
Requires-Dist: pytest-asyncio>=1.0.0; extra == "tests"
Requires-Dist: pytest-mock>=3.14.1; extra == "tests"
Requires-Dist: ruff>=0.12.8; extra == "tests"
Requires-Dist: pytest-cov>=7.0.0; extra == "tests"
Provides-Extra: build
Requires-Dist: setuptools>=80.9.0; extra == "build"
Requires-Dist: wheel>=0.45.1; extra == "build"
Requires-Dist: twine>=6.1.0; extra == "build"
Requires-Dist: cython>=3.1.2; extra == "build"
Requires-Dist: cibuildwheel>=3.0.0; extra == "build"
Requires-Dist: build>=1.2.2.post1; extra == "build"
Provides-Extra: admin
Requires-Dist: invoke>=2.2.0; extra == "admin"
Requires-Dist: google-cloud-firestore>=2.21.0; extra == "admin"
Requires-Dist: firebase-admin>=7.1.0; extra == "admin"
Provides-Extra: benchmark
Requires-Dist: sb-cli>=0.1.5; extra == "benchmark"
Requires-Dist: datasets>=4.2.0; extra == "benchmark"
Requires-Dist: gitpython>=3.1.45; extra == "benchmark"
